[{"id": 1001, "word": "environmental", "pos": "adj.", "meaning": "周围的；环境的 环境的；环保的"}, {"id": 1002, "word": "client", "pos": "n.", "meaning": "客户；顾客；委托人 客户；客户机"}, {"id": 1003, "word": "sector", "pos": "n.", "meaning": "扇形；部门；部分；函数尺"}, {"id": 1004, "word": "context", "pos": "n.", "meaning": "上下文；背景；来龙去脉 n. 上下文 上下文"}, {"id": 1005, "word": "attorney", "pos": "n.", "meaning": "代理人；律师 律师；代理人"}, {"id": 1006, "word": "participant", "pos": "n.", "meaning": "参加者；参与者 a. 有份的；参加的；参与的"}, {"id": 1007, "word": "studio", "pos": "n.", "meaning": "工作室；画室；演播室；电影制片厂"}, {"id": 1008, "word": "assessment", "pos": "n.", "meaning": "评估；估定；评定的款额 评估"}, {"id": 1009, "word": "currently", "pos": "adv.", "meaning": "现在；当前；一般；普通 当前"}, {"id": 1010, "word": "category", "pos": "n.", "meaning": "种类；类项 分类"}, {"id": 1011, "word": "grab", "pos": "n.", "meaning": "抓握；掠夺；强占；东方沿岸帆船 vi. 抓取"}, {"id": 1012, "word": "unemployment", "pos": "n.", "meaning": "失业；失业人数 失业"}, {"id": 1013, "word": "asset", "pos": "n.", "meaning": "资产；有益的东西"}, {"id": 1014, "word": "offence", "pos": "n.", "meaning": "犯罪；冒犯；违反；罪过"}, {"id": 1015, "word": "enterprise", "pos": "n.", "meaning": "企业；事业心；进取心；干事业 企业"}, {"id": 1016, "word": "corporate", "pos": "adj.", "meaning": "社团的；合伙的；公司的 团体的；法人的"}, {"id": 1017, "word": "module", "pos": "n.", "meaning": "组件；模数 模块"}, {"id": 1018, "word": "jack", "pos": "n.", "meaning": "插座；千斤顶；男人 vt. 抬起；提醒"}, {"id": 1019, "word": "theme", "pos": "n.", "meaning": "主题；话题；题目"}, {"id": 1020, "word": "storm", "pos": "n.", "meaning": "暴风雨；骚动；风波；风暴"}, {"id": 1021, "word": "publication", "pos": "n.", "meaning": "出版物；出版；公布 发布"}, {"id": 1022, "word": "expenditure", "pos": "n.", "meaning": "开支；费用；用光；消费额 支出"}, {"id": 1023, "word": "treaty", "pos": "n.", "meaning": "条约；谈判 协议；协定；协商"}, {"id": 1024, "word": "journey", "pos": "n.", "meaning": "旅程；旅行；行程 vi. 旅行 vt. 游历"}, {"id": 1025, "word": "shadow", "pos": "n.", "meaning": "阴影；荫；影子；影像"}, {"id": 1026, "word": "struggle", "pos": "n.", "meaning": "斗争；努力；奋斗 vi. 努力；奋斗"}, {"id": 1027, "word": "conclude", "pos": "vt.", "meaning": "结束；作结论；推断 vi. 结束；推断"}, {"id": 1028, "word": "sum", "pos": "n.", "meaning": "总数；总和；金额；概要"}, {"id": 1029, "word": "analyst", "pos": "n.", "meaning": "分析者；精神分析学家 分析员；化验员"}, {"id": 1030, "word": "imply", "pos": "vt.", "meaning": "暗示；意味 隐含"}, {"id": 1031, "word": "illustrate", "pos": "vt.", "meaning": "举例说明；作图解；阐明 vi. 举例说明"}, {"id": 1032, "word": "shift", "pos": "n.", "meaning": "变化；移动；轮班；手段"}, {"id": 1033, "word": "captain", "pos": "n.", "meaning": "船长；指挥官；海军上校；首领 vt. 率领"}, {"id": 1034, "word": "revenue", "pos": "n.", "meaning": "收入；岁入；税收；税务局 岁入"}, {"id": 1035, "word": "phase", "pos": "n.", "meaning": "时期；局面；方面；位相"}, {"id": 1036, "word": "locate", "pos": "vt.", "meaning": "找出；设于；位于 vi. 定居"}, {"id": 1037, "word": "display", "pos": "n.", "meaning": "显示；陈列；炫耀；显示器 vt. 陈列"}, {"id": 1038, "word": "initiative", "pos": "n.", "meaning": "主动行动；首创精神；主动权 a. 自发的；起始的"}, {"id": 1039, "word": "sequence", "pos": "n.", "meaning": "序列；续发事件；顺序；连续 vt. 按顺序排好 顺序"}, {"id": 1040, "word": "widely", "pos": "adv.", "meaning": "广泛地"}, {"id": 1041, "word": "generate", "pos": "vt.", "meaning": "产生；发生；导致 产生"}, {"id": 1042, "word": "assumption", "pos": "n.", "meaning": "假定；自负；担任；假装 假定"}, {"id": 1043, "word": "curriculum", "pos": "n.", "meaning": "课程 课程；学程"}, {"id": 1044, "word": "trend", "pos": "n.", "meaning": "趋势；倾向；走向 vi. 倾向；转向 趋势"}, {"id": 1045, "word": "escape", "pos": "n.", "meaning": "逃亡；避难设备；逃跑 vi. 逃脱；避开"}, {"id": 1046, "word": "comfortable", "pos": "adj.", "meaning": "舒服的；轻松的 n. 盖被"}, {"id": 1047, "word": "crew", "pos": "n.", "meaning": "全体人员；一群人；全体队员 crow的过去式"}, {"id": 1048, "word": "investigate", "pos": "v.", "meaning": "调查；审查"}, {"id": 1049, "word": "muscle", "pos": "n.", "meaning": "肌肉；臂力 肌"}, {"id": 1050, "word": "notion", "pos": "n.", "meaning": "概念；观念；想法；打算"}, {"id": 1051, "word": "gallery", "pos": "n.", "meaning": "走廊；最高楼座；画廊；收集"}, {"id": 1052, "word": "capture", "pos": "n.", "meaning": "抓取；战利品；捕获之物 vt. 抓取；获得"}, {"id": 1053, "word": "chest", "pos": "n.", "meaning": "胸；胸部；衣柜；箱子 胸"}, {"id": 1054, "word": "ministry", "pos": "n.", "meaning": "部；内阁；服务 部"}, {"id": 1055, "word": "jesus", "pos": "n.", "meaning": "耶稣"}, {"id": 1056, "word": "truly", "pos": "adv.", "meaning": "真实地；不假"}, {"id": 1057, "word": "emphasis", "pos": "n.", "meaning": "强调；加强；重点；强语气"}, {"id": 1058, "word": "thick", "pos": "adj.", "meaning": "厚的；粗壮的；浓的；迟钝的"}, {"id": 1059, "word": "afford", "pos": "vt.", "meaning": "买得起；足以；给予"}, {"id": 1060, "word": "prospect", "pos": "n.", "meaning": "景色；展望 vt. 勘探；勘察 vi. 勘探；有前途"}, {"id": 1061, "word": "narrow", "pos": "n.", "meaning": "狭窄部分；隘路 a. 狭窄的；仔细的；有限的"}, {"id": 1062, "word": "emergency", "pos": "n.", "meaning": "紧急状况；紧急事件；紧急需要 紧急情况"}, {"id": 1063, "word": "inform", "pos": "vt.", "meaning": "通知；使了解；使充满 vi. 提供资料；告发"}, {"id": 1064, "word": "unique", "pos": "adj.", "meaning": "独一无二的；独特的；稀罕的"}, {"id": 1065, "word": "advise", "pos": "vt.", "meaning": "劝告；给...出主意；通知；建议 vi. 提意见"}, {"id": 1066, "word": "ethnic", "pos": "adj.", "meaning": "人种的；种族的 人种的"}, {"id": 1067, "word": "priority", "pos": "n.", "meaning": "优先权；优先 优先级"}, {"id": 1068, "word": "opening", "pos": "n.", "meaning": "开始；口子；穴；揭幕 a. 开始的"}, {"id": 1069, "word": "stress", "pos": "n.", "meaning": "压力；紧迫；强调；重音"}, {"id": 1070, "word": "combination", "pos": "n.", "meaning": "组合；合并；联合 组合图"}, {"id": 1071, "word": "rely", "pos": "vi.", "meaning": "信赖；依赖；信任"}, {"id": 1072, "word": "root", "pos": "n.", "meaning": "根；根本；根源；基础"}, {"id": 1073, "word": "liberal", "pos": "n.", "meaning": "自由主义者 a. 慷慨的；不拘泥的；宽大的；自由主义的"}, {"id": 1074, "word": "appreciate", "pos": "vt.", "meaning": "赏识；鉴别；为...而感激；领会"}, {"id": 1075, "word": "succeed", "pos": "vi.", "meaning": "成功；继承；继续 vt. 继承；接替"}, {"id": 1076, "word": "setting", "pos": "n.", "meaning": "环境；背景；布景；镶嵌"}, {"id": 1077, "word": "upper", "pos": "adj.", "meaning": "上面的；较高的；上级的；上院的"}, {"id": 1078, "word": "interpretation", "pos": "n.", "meaning": "解释；演出；翻译 插值；插值法"}, {"id": 1079, "word": "outcome", "pos": "n.", "meaning": "结果；出口"}, {"id": 1080, "word": "defend", "pos": "vt.", "meaning": "防护；辩护；防卫 作...的辩护律师；辩护"}, {"id": 1081, "word": "alternative", "pos": "n.", "meaning": "两者择一；供替代的选择 a. 两者择一的；供选择的 选择对象"}, {"id": 1082, "word": "wing", "pos": "n.", "meaning": "翅膀；翼；机翼；派别 vt. 给...装上翼"}, {"id": 1083, "word": "catholic", "pos": "n.", "meaning": "天主教徒 a. 天主教的；普遍的；广泛的；宽宏大量的"}, {"id": 1084, "word": "lane", "pos": "n.", "meaning": "小路；巷；弄；单行道"}, {"id": 1085, "word": "crown", "pos": "n.", "meaning": "王冠；王权；顶点 vt. 使成王；加冕"}, {"id": 1086, "word": "coal", "pos": "n.", "meaning": "煤；木炭 v. 加煤"}, {"id": 1087, "word": "approve", "pos": "vt.", "meaning": "赞同；核准；为...提供证据 vi. 赞许"}, {"id": 1088, "word": "zone", "pos": "n.", "meaning": "地带；带；地区 vt. 环绕；使分成地带 vi. 分成区 卡片顶部的三行区"}, {"id": 1089, "word": "variation", "pos": "n.", "meaning": "变更；变化；变种；变奏 变异"}, {"id": 1090, "word": "castle", "pos": "n.", "meaning": "城堡；象棋中的车 vt. 置于城堡中；盘踞于"}, {"id": 1091, "word": "motion", "pos": "n.", "meaning": "移动；手势；动作；意向"}, {"id": 1092, "word": "apparent", "pos": "adj.", "meaning": "清晰可见的；显然的；表面上的 外在的"}, {"id": 1093, "word": "membership", "pos": "n.", "meaning": "会员的资格；全体会员；会员数目 会员资格；成员资格"}, {"id": 1094, "word": "pilot", "pos": "n.", "meaning": "飞行员；领航员；航船者；导向器"}, {"id": 1095, "word": "ultimately", "pos": "adv.", "meaning": "最后；最终 最后；终究；总之"}, {"id": 1096, "word": "persuade", "pos": "vt.", "meaning": "劝；使相信；恳求；敦促"}, {"id": 1097, "word": "cope", "pos": "vi.", "meaning": "竞争；应付 n. 长袍"}, {"id": 1098, "word": "politician", "pos": "n.", "meaning": "政客；政治家；从事党派政治的人 政客；政治家"}, {"id": 1099, "word": "steal", "pos": "vt.", "meaning": "剽窃；偷偷地做；偷窃；vi. 窃取"}, {"id": 1100, "word": "pursue", "pos": "vt.", "meaning": "追赶；追踪；追随；追求"}, {"id": 1101, "word": "incident", "pos": "n.", "meaning": "事件；事变；小事 a. 附带的；易于发生的"}, {"id": 1102, "word": "slip", "pos": "n.", "meaning": "滑；滑行；事故；溜"}, {"id": 1103, "word": "percentage", "pos": "n.", "meaning": "百分比；比率；部分；可能性 百分比"}, {"id": 1104, "word": "winner", "pos": "n.", "meaning": "胜利者；优胜者 取胜者"}, {"id": 1105, "word": "soil", "pos": "n.", "meaning": "土壤；土地；国家；国土"}, {"id": 1106, "word": "index", "pos": "n.", "meaning": "索引；指针；指数；指标 vt. 编入索引中"}, {"id": 1107, "word": "surgery", "pos": "n.", "meaning": "外科；手术；手术室；换球术"}, {"id": 1108, "word": "jewish", "pos": "adj.", "meaning": "犹太人的；犹太族的"}, {"id": 1109, "word": "valley", "pos": "n.", "meaning": "山谷；溪谷；流域；凹地 谷"}, {"id": 1110, "word": "blame", "pos": "n.", "meaning": "过失；责备 vt. 责备；归咎于"}, {"id": 1111, "word": "derive", "pos": "vt.", "meaning": "得自 vi. 起源"}, {"id": 1112, "word": "estimate", "pos": "n.", "meaning": "估计；判断 vt. 估计；评价；判断 vi. 估计"}, {"id": 1113, "word": "criterion", "pos": "n.", "meaning": "标准；准则；规范 判据"}, {"id": 1114, "word": "golf", "pos": "n.", "meaning": "高尔夫球 vi. 打高尔夫球"}, {"id": 1115, "word": "square", "pos": "n.", "meaning": "正方形；街区；广场；平方"}, {"id": 1116, "word": "crazy", "pos": "adj.", "meaning": "发狂的；狂热的"}, {"id": 1117, "word": "vital", "pos": "adj.", "meaning": "生命的；重要的；充满活力的；生死攸关的"}, {"id": 1118, "word": "recover", "pos": "vt.", "meaning": "重新获得；恢复；复原；拯救 vi. 痊愈"}, {"id": 1119, "word": "chain", "pos": "n.", "meaning": "链；枷锁；束缚 vt. 用铁练锁住；束缚"}, {"id": 1120, "word": "specialist", "pos": "n.", "meaning": "专门医师；专家 a. 专业的；专家的"}, {"id": 1121, "word": "governor", "pos": "n.", "meaning": "(美)州长；(英)总督；统治者；管理者"}, {"id": 1122, "word": "characteristic", "pos": "n.", "meaning": "特性；特征；特色 a. 特性的；特有的"}, {"id": 1123, "word": "tone", "pos": "n.", "meaning": "音调；音质；语调；语气"}, {"id": 1124, "word": "kick", "pos": "n.", "meaning": "踢；反冲；后座力；凹底 vi. 踢"}, {"id": 1125, "word": "engineering", "pos": "n.", "meaning": "工程学；工程；操纵 机器；机器学"}, {"id": 1126, "word": "ancient", "pos": "adj.", "meaning": "古代的；古老的；年老的；旧的"}, {"id": 1127, "word": "rating", "pos": "n.", "meaning": "等级；额定功率；责骂 等级评定"}, {"id": 1128, "word": "golden", "pos": "adj.", "meaning": "金的；含金的；金色的；贵重的"}, {"id": 1129, "word": "request", "pos": "n.", "meaning": "请求；需要；申请书 vt. 请求；要求"}, {"id": 1130, "word": "foundation", "pos": "n.", "meaning": "基础；根据；建立 地基"}, {"id": 1131, "word": "solve", "pos": "vt.", "meaning": "解决；付给；溶解 vt. 求解 vi. 求解 求解"}, {"id": 1132, "word": "deputy", "pos": "n.", "meaning": "副手；代理人"}, {"id": 1133, "word": "landscape", "pos": "n.", "meaning": "风景；山水；风景画 vi. 从事景观美化 vt. 美化...景观 横向"}, {"id": 1134, "word": "representation", "pos": "n.", "meaning": "表示法；表现；陈述；代表 表示法指定"}, {"id": 1135, "word": "rare", "pos": "adj.", "meaning": "稀罕的；罕有的；珍奇的；稀薄的"}, {"id": 1136, "word": "frame", "pos": "n.", "meaning": "框；结构；体格 vt. 构成；设计"}, {"id": 1137, "word": "forth", "pos": "adv.", "meaning": "往前；以后；向外"}, {"id": 1138, "word": "typical", "pos": "adj.", "meaning": "典型的；象征性的 典型的"}, {"id": 1139, "word": "eliminate", "pos": "vt.", "meaning": "除去；排除；剔除；消除"}, {"id": 1140, "word": "host", "pos": "n.", "meaning": "主人；旅馆老板；节目主持人 vt. 当主人招待；作...节目主持人 主机"}, {"id": 1141, "word": "observation", "pos": "n.", "meaning": "观察；注意；观测；观察力 观察"}, {"id": 1142, "word": "producer", "pos": "n.", "meaning": "生产者；制作者；制作人 发生器；(炉煤气)发生炉"}, {"id": 1143, "word": "impression", "pos": "n.", "meaning": "印象；意念；盖印；印记"}, {"id": 1144, "word": "meanwhile", "pos": "n.", "meaning": "其时；其间 adv. 同时；于此时"}, {"id": 1145, "word": "neighbour", "pos": "n.", "meaning": "邻居；邻接的东西；邻国；邻座"}, {"id": 1146, "word": "regime", "pos": "n.", "meaning": "政权；当权期间；政体；社会制度"}, {"id": 1147, "word": "capable", "pos": "adj.", "meaning": "有能力的；能的；能干的"}, {"id": 1148, "word": "attach", "pos": "vt.", "meaning": "附上；使依附；使附属；使喜爱"}, {"id": 1149, "word": "fix", "pos": "vt.", "meaning": "使固定；修理；准备；安装"}, {"id": 1150, "word": "grand", "pos": "adj.", "meaning": "庄重的；壮观的；显赫的；重大的"}, {"id": 1151, "word": "fashion", "pos": "n.", "meaning": "流行；风尚；时样 vt. 形成；造"}, {"id": 1152, "word": "mirror", "pos": "n.", "meaning": "镜子；写真；典范 vt. 反映；映出"}, {"id": 1153, "word": "coast", "pos": "n.", "meaning": "海岸；滑坡 v. 沿海岸而行"}, {"id": 1154, "word": "atmosphere", "pos": "n.", "meaning": "大气；空气；气氛 大气；大气压"}, {"id": 1155, "word": "smart", "pos": "adj.", "meaning": "聪明的；漂亮的；刺痛的；剧烈的"}, {"id": 1156, "word": "mass", "pos": "n.", "meaning": "块；大多数；质量；大量"}, {"id": 1157, "word": "revolution", "pos": "n.", "meaning": "革命；大变革；旋转；转数"}, {"id": 1158, "word": "complain", "pos": "v.", "meaning": "抱怨；抗议；控诉"}, {"id": 1159, "word": "topic", "pos": "n.", "meaning": "主题；论题；话题"}, {"id": 1160, "word": "tear", "pos": "n.", "meaning": "泪滴；眼泪；撕；扯"}, {"id": 1161, "word": "variable", "pos": "n.", "meaning": "易变的事物；变数；可变物；变量 a. 可变的"}, {"id": 1162, "word": "distinction", "pos": "n.", "meaning": "区别"}, {"id": 1163, "word": "perception", "pos": "n.", "meaning": "知觉；感觉；领悟力；获取 知觉"}, {"id": 1164, "word": "secret", "pos": "n.", "meaning": "秘密；机密；秘诀；秘方 a. 秘密的"}, {"id": 1165, "word": "mechanism", "pos": "n.", "meaning": "机械；机构；结构；机理"}, {"id": 1166, "word": "external", "pos": "n.", "meaning": "外部；外面 a. 外部的；客观的；表面的"}, {"id": 1167, "word": "tank", "pos": "n.", "meaning": "槽；箱；柜；罐"}, {"id": 1168, "word": "defendant", "pos": "n.", "meaning": "被告 被告方"}, {"id": 1169, "word": "iron", "pos": "n.", "meaning": "铁；熨斗；铁器；坚强"}, {"id": 1170, "word": "servant", "pos": "n.", "meaning": "仆人；有用物；公务员；雇员 受雇人"}, {"id": 1171, "word": "roof", "pos": "n.", "meaning": "屋顶；室顶 vt. 给...盖屋顶；遮蔽"}, {"id": 1172, "word": "bond", "pos": "n.", "meaning": "捆绑物；结合；债券；契约"}, {"id": 1173, "word": "advance", "pos": "n.", "meaning": "前进；进展；行过的路程 vi. 前进；进展"}, {"id": 1174, "word": "welfare", "pos": "n.", "meaning": "福利；安宁；幸福；福利事业 a. 福利的"}, {"id": 1175, "word": "era", "pos": "n.", "meaning": "时代；纪元；时期"}, {"id": 1176, "word": "engineer", "pos": "n.", "meaning": "工程师；工兵 vt. 设计；监造；精明地处理"}, {"id": 1177, "word": "expectation", "pos": "n.", "meaning": "期待；指望；展望 期望值"}, {"id": 1178, "word": "drawing", "pos": "n.", "meaning": "图画；制图；拉 绘图"}, {"id": 1179, "word": "accuse", "pos": "vt.", "meaning": "指责；控告；归咎于 vi. 指责；控告"}, {"id": 1180, "word": "motor", "pos": "n.", "meaning": "马达；发动机；原动力；汽车 a. 马达的"}, {"id": 1181, "word": "somewhat", "pos": "n.", "meaning": "某物；几分 adv. 多少；几分"}, {"id": 1182, "word": "pour", "pos": "n.", "meaning": "流出；倾泻；骤雨 vt. 倒；灌"}, {"id": 1183, "word": "origin", "pos": "n.", "meaning": "起源；起因；出身；开端 原点"}, {"id": 1184, "word": "grey", "pos": "n.", "meaning": "灰色 a. 灰色的；阴沉的 v. (使)成灰色"}, {"id": 1185, "word": "stir", "pos": "n.", "meaning": "骚动；轰动；搅动；监狱 vt. 移动"}, {"id": 1186, "word": "negotiation", "pos": "n.", "meaning": "谈判；磋商；交涉 谈判；协商"}, {"id": 1187, "word": "accompany", "pos": "vt.", "meaning": "陪伴；伴随；补充；为...伴奏 vi. 伴奏"}, {"id": 1188, "word": "establishment", "pos": "n.", "meaning": "确立；制定；设施 企业；公司"}, {"id": 1189, "word": "hence", "pos": "adv.", "meaning": "因此；从此"}, {"id": 1190, "word": "liability", "pos": "n.", "meaning": "责任；债务；倾向 责任；义务"}, {"id": 1191, "word": "unfortunately", "pos": "adv.", "meaning": "恐怕；不幸的是"}, {"id": 1192, "word": "warning", "pos": "n.", "meaning": "警告；预告；预兆；通知 警告"}, {"id": 1193, "word": "hero", "pos": "n.", "meaning": "英雄；超越常人者；男主角"}, {"id": 1194, "word": "minor", "pos": "n.", "meaning": "未成年人；副修科目 a. 较小的；二流的；未成年的 vi. 副修 次要"}, {"id": 1195, "word": "height", "pos": "n.", "meaning": "高度；海拔；高地；顶点 高度"}, {"id": 1196, "word": "stretch", "pos": "n.", "meaning": "伸展；张开；连绵；一段路"}, {"id": 1197, "word": "constant", "pos": "n.", "meaning": "常数；恒量 a. 不变的；一定的；时常的 常量"}, {"id": 1198, "word": "ideal", "pos": "n.", "meaning": "理想；典范；观念；思想"}, {"id": 1199, "word": "seed", "pos": "n.", "meaning": "种子；籽；萌芽；子孙"}, {"id": 1200, "word": "withdraw", "pos": "vt.", "meaning": "撤回；取回；撤消；使撤退"}, {"id": 1201, "word": "significance", "pos": "n.", "meaning": "重要性；意义；意味 有效；有效性"}, {"id": 1202, "word": "pepper", "pos": "n.", "meaning": "胡椒粉；胡椒；辣椒 胡椒；辣椒"}, {"id": 1203, "word": "severe", "pos": "adj.", "meaning": "严格的；尖锐的；严肃的；严重的"}, {"id": 1204, "word": "intervention", "pos": "n.", "meaning": "插入；介入；调停 干预"}, {"id": 1205, "word": "terrible", "pos": "adj.", "meaning": "可怕的；令人恐惧的；极坏的"}, {"id": 1206, "word": "tip", "pos": "n.", "meaning": "顶；尖端；梢；末端"}, {"id": 1207, "word": "india", "pos": "n.", "meaning": "印度"}, {"id": 1208, "word": "cite", "pos": "vt.", "meaning": "引用；引证；表彰 引证；指引"}, {"id": 1209, "word": "prisoner", "pos": "n.", "meaning": "囚犯；犯人；战俘 犯人；囚犯"}, {"id": 1210, "word": "vast", "pos": "adj.", "meaning": "巨大的；广大的；非常的；大量的"}, {"id": 1211, "word": "champion", "pos": "n.", "meaning": "冠军；拥护者；战士 vt. 保卫；拥护 a. 优胜的"}, {"id": 1212, "word": "gray", "pos": "n.", "meaning": "灰色；暗淡 a. 灰色的；灰白的；面色苍白的"}, {"id": 1213, "word": "exclude", "pos": "vt.", "meaning": "除外；排除；排斥 除外(诊断)"}, {"id": 1214, "word": "oppose", "pos": "vt.", "meaning": "反对；以...对抗；抗争 vi. 反对"}, {"id": 1215, "word": "christ", "pos": "n.", "meaning": "基督；救世主"}, {"id": 1216, "word": "convention", "pos": "n.", "meaning": "大会；协定；惯例；约定 约定"}, {"id": 1217, "word": "contemporary", "pos": "n.", "meaning": "同时代的人 a. 同时代的；属于同一时期的"}, {"id": 1218, "word": "multiple", "pos": "n.", "meaning": "倍数；并联 a. 多样的；许多的；多功能的"}, {"id": 1219, "word": "switch", "pos": "n.", "meaning": "开关；电闸；转换；软枝"}, {"id": 1220, "word": "criminal", "pos": "n.", "meaning": "罪犯；犯人；刑事 a. 犯了罪的；刑事的"}, {"id": 1221, "word": "core", "pos": "n.", "meaning": "核心；果心；要点 vt. 挖...的核 内核；核心网"}, {"id": 1222, "word": "rush", "pos": "n.", "meaning": "匆促；冲进；急流；灯心草 vi. 冲"}, {"id": 1223, "word": "specifically", "pos": "adv.", "meaning": "特定地；明确地；按特性"}, {"id": 1224, "word": "justify", "pos": "vt.", "meaning": "替...辩护；证明 vi. 证明合法 段落重排；两端对齐"}, {"id": 1225, "word": "signal", "pos": "n.", "meaning": "信号；暗号；近因；导火线 vt. 向...作信号"}, {"id": 1226, "word": "rail", "pos": "n.", "meaning": "横杆；围栏；栏杆；铁轨"}, {"id": 1227, "word": "diet", "pos": "n.", "meaning": "日常饮食；议会 vt. 照规定饮食 vi. 忌食"}, {"id": 1228, "word": "strongly", "pos": "adv.", "meaning": "强有力地；坚强地；激烈地"}, {"id": 1229, "word": "rapidly", "pos": "adv.", "meaning": "飞快地；迅速地；赶紧地"}, {"id": 1230, "word": "resolution", "pos": "n.", "meaning": "解析；决心；坚定；决定"}, {"id": 1231, "word": "witness", "pos": "n.", "meaning": "证人；目击者；证据；证词 vt. 目击"}, {"id": 1232, "word": "barely", "pos": "adv.", "meaning": "几乎不"}, {"id": 1233, "word": "emphasize", "pos": "vt.", "meaning": "强调；加强语气；着重"}, {"id": 1234, "word": "plenty", "pos": "n.", "meaning": "充分；很多；丰富 a. 很多的；足够的"}, {"id": 1235, "word": "achievement", "pos": "n.", "meaning": "完成；成就；功业"}, {"id": 1236, "word": "proud", "pos": "adj.", "meaning": "骄傲的；自大的；自豪的；辉煌的"}, {"id": 1237, "word": "faculty", "pos": "n.", "meaning": "才能；能力；全体教员；(大学的)系 能力"}, {"id": 1238, "word": "gap", "pos": "n.", "meaning": "缝隙；缺口；间断；间距"}, {"id": 1239, "word": "weak", "pos": "adj.", "meaning": "不牢固的；弱的；虚弱的；软弱的"}, {"id": 1240, "word": "occupy", "pos": "vt.", "meaning": "占领；占(时间、空间等)；住进；担任"}, {"id": 1241, "word": "definitely", "pos": "adv.", "meaning": "明确无疑地；清楚地"}, {"id": 1242, "word": "bomb", "pos": "n.", "meaning": "炸弹 vt. 轰炸；投弹于 vi. 失败"}, {"id": 1243, "word": "permanent", "pos": "adj.", "meaning": "永久的；不变的；固定的；持久的 n. 烫发 永久的"}, {"id": 1244, "word": "enormous", "pos": "adj.", "meaning": "巨大的；庞大的"}, {"id": 1245, "word": "massive", "pos": "adj.", "meaning": "大而重的；宽大的；宏伟的 大块的；整块的"}, {"id": 1246, "word": "complaint", "pos": "n.", "meaning": "诉苦；抱怨；控诉 陈诉；病"}, {"id": 1247, "word": "shock", "pos": "n.", "meaning": "震动；冲突；震惊；冲击"}, {"id": 1248, "word": "wheel", "pos": "n.", "meaning": "轮子；车轮；轮；方向盘"}, {"id": 1249, "word": "decline", "pos": "n.", "meaning": "衰退；跌落；下降 vt. 使降低；婉谢 vi. 下降"}, {"id": 1250, "word": "invest", "pos": "vt.", "meaning": "投资；花费；笼罩；授予 vi. 投资"}]